tinno_mcp_git/__init__.py
tinno_mcp_git/__main__.py
tinno_mcp_git/server.py
tinno_mcp_git-1.0.5.dist-info/METADATA
tinno_mcp_git-1.0.5.dist-info/WHEEL
tinno_mcp_git-1.0.5.dist-info/entry_points.txt
tinno_mcp_git-1.0.5.dist-info/licenses/LICENSE
tinno_mcp_git-1.0.5.dist-info/RECORD
