Metadata-Version: 2.4
Name: tinno-mcp-git
Version: 1.0.5
Summary: A Model Context Protocol server providing tools to read, search, and manipulate Git repositories programmatically via LLMs
Author: Anthropic, PBC.
Maintainer-email: "wei.xiao" <wei.xiao@tinno.com>
License: MIT
License-File: LICENSE
Keywords: automation,git,llm,mcp
Classifier: Development Status :: 4 - Beta
Classifier: Intended Audience :: Developers
Classifier: License :: OSI Approved :: MIT License
Classifier: Programming Language :: Python :: 3
Classifier: Programming Language :: Python :: 3.11
Requires-Python: >=3.10
Requires-Dist: click>=8.1.7
Requires-Dist: gitpython>=3.1.43
Requires-Dist: mcp>=1.0.0
Requires-Dist: pydantic>=2.0.0
